dagctl/__init__.py
dagctl/__main__.py
dagctl/auth_commands.py
dagctl/cli.py
dagctl/dagctl_config.py
dagctl/project_commands.py
dagctl/protection.py
dagctl/state.py
dagctl-0.1.6.dist-info/METADATA
dagctl-0.1.6.dist-info/WHEEL
dagctl-0.1.6.dist-info/entry_points.txt
dagctl-0.1.6.dist-info/top_level.txt
dagctl-0.1.6.dist-info/RECORD
