Metadata-Version: 2.1
Name: dagctl
Version: 0.1.6
Summary: CLI tool for managing SQLMesh projects with dagctl-hosted state databases
Author-email: Scalecraft <support@scalecraft.dev>
License: Apache-2.0
Project-URL: Homepage, https://dagctl.io
Project-URL: Documentation, https://docs.dagctl.io
Project-URL: Repository, https://github.com/scalecraft-dev/dagctl
Project-URL: Issues, https://github.com/scalecraft-dev/dagctl/issues
Keywords: sqlmesh,data,analytics,sql,dagctl,state-management
Classifier: Development Status :: 4 - Beta
Classifier: Intended Audience :: Developers
Classifier: Intended Audience :: Information Technology
Classifier: License :: OSI Approved :: Apache Software License
Classifier: Operating System :: OS Independent
Classifier: Programming Language :: Python :: 3
Classifier: Programming Language :: Python :: 3.9
Classifier: Programming Language :: Python :: 3.10
Classifier: Programming Language :: Python :: 3.11
Classifier: Programming Language :: Python :: 3.12
Classifier: Topic :: Database
Classifier: Topic :: Software Development :: Libraries :: Python Modules
Classifier: Typing :: Typed
Requires-Python: >=3.9
Requires-Dist: click>=8.1.0
Requires-Dist: requests>=2.31.0
Requires-Dist: rich>=13.0.0
Requires-Dist: pyyaml>=6.0
Requires-Dist: python-dotenv>=1.0.0
Provides-Extra: dev
Requires-Dist: pytest>=7.4.0; extra == "dev"
Requires-Dist: pytest-cov>=4.1.0; extra == "dev"
Requires-Dist: black>=23.0.0; extra == "dev"
Requires-Dist: ruff>=0.0.280; extra == "dev"
Requires-Dist: mypy>=1.4.0; extra == "dev"
